cordstore/__init__.py
cordstore/channel_storage.py
cordstore/errors.py
cordstore/uploaded_file.py
cordstore/webhook_storage.py
cordstore-0.0.3.dist-info/LICENSE
cordstore-0.0.3.dist-info/METADATA
cordstore-0.0.3.dist-info/WHEEL
cordstore-0.0.3.dist-info/top_level.txt
cordstore-0.0.3.dist-info/RECORD
